Workbook

Sheet Test Cases
A1: Category | B1: Test Case ID | C1: Test Case Description | D1: Steps to Test | E1: Expected Result | F1: Status | G1: Tested By | H1: Date Tested | I1: Notes
A2: 1. Basic Transaction Flow | B2: TC-001 | C2: Create new transaction (draft) | D2: 1. Navigate to Daily Sales 2. Click "New Transaction" 3. Fill in patient, date, record number 4. Click "Save Draft" | E2: Transaction saved as draft, shows in draft list with "Draft" badge | F2: Not Tested
A3: 1. Basic Transaction Flow | B3: TC-002 | C3: Add products to transaction | D3: 1. Open transaction 2. Select product from dropdown 3. Enter amount 4. Click "Save Draft" | E3: Product appears in transaction details, total calculates correctly | F3: Not Tested
A4: 1. Basic Transaction Flow | B4: TC-003 | C4: Add multiple products | D4: 1. Add product 1 with amount 2. Add product 2 with amount 3. Save draft | E4: All products saved, totals sum correctly | F4: Not Tested
A5: 1. Basic Transaction Flow | B5: TC-004 | C5: Add payment methods (tenders) | D5: 1. Select tender (Cash/Credit/etc) 2. Enter amount 3. Save draft | E5: Payment method saved, balance calculated (total - payment) | F5: Not Tested
A6: 1. Basic Transaction Flow | B6: TC-005 | C6: Add line-level discount | D6: 1. Add product 2. Enter discount amount 3. Save | E6: Discount applied to product line, net amount = amount - discount | F6: Not Tested
A7: 1. Basic Transaction Flow | B7: TC-006 | C7: Add transaction-level discount | D7: 1. Add products 2. Enter transaction discount 3. Save | E7: Discount applied to total, final total reduced | F7: Not Tested
A8: 1. Basic Transaction Flow | B8: TC-007 | C8: Edit draft transaction | D8: 1. Open draft transaction 2. Modify fields 3. Save | E8: Changes saved, audit log shows update | F8: Not Tested
A9: 1. Basic Transaction Flow | B9: TC-008 | C9: Delete draft transaction | D9: 1. Open draft 2. Click Delete 3. Confirm | E9: Transaction removed from list | F9: Not Tested
A10: 1. Basic Transaction Flow | B10: TC-009 | C10: Submit transaction for approval | D10: 1. Open draft 2. Click "Save & Submit" 3. Confirm | E10: Status changes to "Submitted", shows submitted date, appears in pending approvals | F10: Not Tested
A11: 2. Approval Workflow | B11: TC-101 | C11: View pending approvals (Admin) | D11: 1. Login as Admin 2. Navigate to Pending Approvals | E11: All submitted transactions appear in list | F11: Not Tested
A12: 2. Approval Workflow | B12: TC-102 | C12: Approve transaction | D12: 1. View pending transaction 2. Click "Approve" 3. Confirm | E12: Status changes to "Approved", badge shows green, removed from pending list, audit log updated | F12: Not Tested
A13: 2. Approval Workflow | B13: TC-103 | C13: Disapprove transaction (return to draft) | D13: 1. View submitted transaction 2. Click "Return to Draft" 3. Enter reason 4. Submit | E13: Status returns to "Draft", reason recorded in description, audit log shows return with reason | F13: Not Tested
... A43: 7. Edge Cases & Validation | B43: TC-606 | C43: Cannot delete submitted transaction | D43: 1. Open submitted transaction 2. Check for delete button | E43: Delete button not available | F43: Not Tested

Sheet Summary
A1: Category | B1: Total Tests | C1: Passed | D1: Failed | E1: Not Tested | F1: Pass %
A2: 1. Basic Transaction Flow | B2: =COUNTIF('Test Cases'!$A:$A,A2) -> 0 | C2: =COUNTIFS('Test Cases'!$A:$A,A2,'Test Cases'!$F:$F,"Passed") -> 0 | D2: =COUNTIFS('Test Cases'!$A:$A,A2,'Test Cases'!$F:$F,"Failed") -> 0 | E2: =COUNTIFS('Test Cases'!$A:$A,A2,'Test Cases'!$F:$F,"Not Tested") -> 0 | F2: =IF(B2=0,"0%",TEXT(C2/B2,"0%")) -> 0
A3: 2. Approval Workflow | B3: =COUNTIF('Test Cases'!$A:$A,A3) -> 0 | C3: =COUNTIFS('Test Cases'!$A:$A,A3,'Test Cases'!$F:$F,"Passed") -> 0 | D3: =COUNTIFS('Test Cases'!$A:$A,A3,'Test Cases'!$F:$F,"Failed") -> 0 | E3: =COUNTIFS('Test Cases'!$A:$A,A3,'Test Cases'!$F:$F,"Not Tested") -> 0 | F3: =IF(B3=0,"0%",TEXT(C3/B3,"0%")) -> 0
A4: 3. Cancellation Workflow | B4: =COUNTIF('Test Cases'!$A:$A,A4) -> 0 | C4: =COUNTIFS('Test Cases'!$A:$A,A4,'Test Cases'!$F:$F,"Passed") -> 0 | D4: =COUNTIFS('Test Cases'!$A:$A,A4,'Test Cases'!$F:$F,"Failed") -> 0 | E4: =COUNTIFS('Test Cases'!$A:$A,A4,'Test Cases'!$F:$F,"Not Tested") -> 0 | F4: =IF(B4=0,"0%",TEXT(C4/B4,"0%")) -> 0
A5: 4. Audit Trail & History | B5: =COUNTIF('Test Cases'!$A:$A,A5) -> 0 | C5: =COUNTIFS('Test Cases'!$A:$A,A5,'Test Cases'!$F:$F,"Passed") -> 0 | D5: =COUNTIFS('Test Cases'!$A:$A,A5,'Test Cases'!$F:$F,"Failed") -> 0 | E5: =COUNTIFS('Test Cases'!$A:$A,A5,'Test Cases'!$F:$F,"Not Tested") -> 0 | F5: =IF(B5=0,"0%",TEXT(C5/B5,"0%")) -> 0
A6: 5. Patient Management | B6: =COUNTIF('Test Cases'!$A:$A,A6) -> 0 | C6: =COUNTIFS('Test Cases'!$A:$A,A6,'Test Cases'!$F:$F,"Passed") -> 0 | D6: =COUNTIFS('Test Cases'!$A:$A,A6,'Test Cases'!$F:$F,"Failed") -> 0 | E6: =COUNTIFS('Test Cases'!$A:$A,A6,'Test Cases'!$F:$F,"Not Tested") -> 0 | F6: =IF(B6=0,"0%",TEXT(C6/B6,"0%")) -> 0
A7: 6. Navigation & UI | B7: =COUNTIF('Test Cases'!$A:$A,A7) -> 0 | C7: =COUNTIFS('Test Cases'!$A:$A,A7,'Test Cases'!$F:$F,"Passed") -> 0 | D7: =COUNTIFS('Test Cases'!$A:$A,A7,'Test Cases'!$F:$F,"Failed") -> 0 | E7: =COUNTIFS('Test Cases'!$A:$A,A7,'Test Cases'!$F:$F,"Not Tested") -> 0 | F7: =IF(B7=0,"0%",TEXT(C7/B7,"0%")) -> 0
A8: 7. Edge Cases & Validation | B8: =COUNTIF('Test Cases'!$A:$A,A8) -> 0 | C8: =COUNTIFS('Test Cases'!$A:$A,A8,'Test Cases'!$F:$F,"Passed") -> 0 | D8: =COUNTIFS('Test Cases'!$A:$A,A8,'Test Cases'!$F:$F,"Failed") -> 0 | E8: =COUNTIFS('Test Cases'!$A:$A,A8,'Test Cases'!$F:$F,"Not Tested") -> 0 | F8: =IF(B8=0,"0%",TEXT(C8/B8,"0%")) -> 0
A9: TOTAL | B9: =SUM(B2:B8) -> 0 | C9: =SUM(C2:C8) -> 0 | D9: =SUM(D2:D8) -> 0 | E9: =SUM(E2:E8) -> 0 | F9: =IF(B9=0,"0%",TEXT(C9/B9,"0%")) -> 0
